pytweetselenium/__init__.py
pytweetselenium/get_content.py
pytweetselenium/get_page_source.py
pytweetselenium/main.py
pytweet_selenium-1.0.0.dist-info/LICENSE
pytweet_selenium-1.0.0.dist-info/METADATA
pytweet_selenium-1.0.0.dist-info/WHEEL
pytweet_selenium-1.0.0.dist-info/top_level.txt
pytweet_selenium-1.0.0.dist-info/RECORD
