Metadata-Version: 2.1
Name: pytweet-selenium
Version: 1.0.0
Summary: Get tweet content using selenium
Home-page: https://github.com/AlexanderJiazx/pytweet.git
Author: Alexander
Author-email: hellolightning321@gmail.com
Classifier: Programming Language :: Python :: 3
Classifier: License :: OSI Approved :: MIT License
Classifier: Operating System :: OS Independent
Requires-Python: >=3.6
License-File: LICENSE
Requires-Dist: selenium
Requires-Dist: bs4
Requires-Dist: requests
